{
  "symbol": "ETHBTC",
  "interval": "15m",
  "days": 1,
  "source": "https://api.binance.com/api/v3/klines",
  "fetched_at": "2026-06-05T23:06:38.157359+00:00",
  "bar_count": 96,
  "bars": [
    {
      "time": "2026-06-04T23:15:00+00:00",
      "open_time_ms": 1780614900000,
      "open": 0.02783,
      "high": 0.02783,
      "low": 0.02772,
      "close": 0.02774,
      "volume": 41.7856,
      "close_time_ms": 1780615799999,
      "quote_volume": 1.15997151,
      "trades": 290
    },
    {
      "time": "2026-06-04T23:30:00+00:00",
      "open_time_ms": 1780615800000,
      "open": 0.02775,
      "high": 0.02776,
      "low": 0.02773,
      "close": 0.02776,
      "volume": 17.6608,
      "close_time_ms": 1780616699999,
      "quote_volume": 0.49006994,
      "trades": 193
    },
    {
      "time": "2026-06-04T23:45:00+00:00",
      "open_time_ms": 1780616700000,
      "open": 0.02776,
      "high": 0.02776,
      "low": 0.02772,
      "close": 0.02772,
      "volume": 38.6757,
      "close_time_ms": 1780617599999,
      "quote_volume": 1.0727072,
      "trades": 226
    },
    {
      "time": "2026-06-05T00:00:00+00:00",
      "open_time_ms": 1780617600000,
      "open": 0.02771,
      "high": 0.02772,
      "low": 0.02769,
      "close": 0.0277,
      "volume": 434.9205,
      "close_time_ms": 1780618499999,
      "quote_volume": 12.0474671,
      "trades": 665
    },
    {
      "time": "2026-06-05T00:15:00+00:00",
      "open_time_ms": 1780618500000,
      "open": 0.02771,
      "high": 0.02773,
      "low": 0.02768,
      "close": 0.02773,
      "volume": 640.2922,
      "close_time_ms": 1780619399999,
      "quote_volume": 17.73388587,
      "trades": 1201
    },
    {
      "time": "2026-06-05T00:30:00+00:00",
      "open_time_ms": 1780619400000,
      "open": 0.02774,
      "high": 0.02778,
      "low": 0.02772,
      "close": 0.02777,
      "volume": 23.7199,
      "close_time_ms": 1780620299999,
      "quote_volume": 0.65839909,
      "trades": 206
    },
    {
      "time": "2026-06-05T00:45:00+00:00",
      "open_time_ms": 1780620300000,
      "open": 0.02776,
      "high": 0.02778,
      "low": 0.02774,
      "close": 0.02775,
      "volume": 37.8504,
      "close_time_ms": 1780621199999,
      "quote_volume": 1.05071713,
      "trades": 448
    },
    {
      "time": "2026-06-05T01:00:00+00:00",
      "open_time_ms": 1780621200000,
      "open": 0.02775,
      "high": 0.02775,
      "low": 0.02767,
      "close": 0.02772,
      "volume": 99.2407,
      "close_time_ms": 1780622099999,
      "quote_volume": 2.74940869,
      "trades": 647
    },
    {
      "time": "2026-06-05T01:15:00+00:00",
      "open_time_ms": 1780622100000,
      "open": 0.02772,
      "high": 0.02776,
      "low": 0.02769,
      "close": 0.02771,
      "volume": 35.0505,
      "close_time_ms": 1780622999999,
      "quote_volume": 0.97130879,
      "trades": 329
    },
    {
      "time": "2026-06-05T01:30:00+00:00",
      "open_time_ms": 1780623000000,
      "open": 0.02771,
      "high": 0.02775,
      "low": 0.02769,
      "close": 0.0277,
      "volume": 39.4692,
      "close_time_ms": 1780623899999,
      "quote_volume": 1.09433883,
      "trades": 323
    },
    {
      "time": "2026-06-05T01:45:00+00:00",
      "open_time_ms": 1780623900000,
      "open": 0.02771,
      "high": 0.02774,
      "low": 0.02767,
      "close": 0.02768,
      "volume": 57.8829,
      "close_time_ms": 1780624799999,
      "quote_volume": 1.60329092,
      "trades": 435
    },
    {
      "time": "2026-06-05T02:00:00+00:00",
      "open_time_ms": 1780624800000,
      "open": 0.02767,
      "high": 0.02767,
      "low": 0.02758,
      "close": 0.02766,
      "volume": 172.0698,
      "close_time_ms": 1780625699999,
      "quote_volume": 4.75371924,
      "trades": 1054
    },
    {
      "time": "2026-06-05T02:15:00+00:00",
      "open_time_ms": 1780625700000,
      "open": 0.02766,
      "high": 0.02772,
      "low": 0.02764,
      "close": 0.0277,
      "volume": 126.5805,
      "close_time_ms": 1780626599999,
      "quote_volume": 3.50209966,
      "trades": 740
    },
    {
      "time": "2026-06-05T02:30:00+00:00",
      "open_time_ms": 1780626600000,
      "open": 0.0277,
      "high": 0.02771,
      "low": 0.02761,
      "close": 0.02767,
      "volume": 75.0144,
      "close_time_ms": 1780627499999,
      "quote_volume": 2.07412093,
      "trades": 658
    },
    {
      "time": "2026-06-05T02:45:00+00:00",
      "open_time_ms": 1780627500000,
      "open": 0.02767,
      "high": 0.02772,
      "low": 0.02763,
      "close": 0.02763,
      "volume": 51.451,
      "close_time_ms": 1780628399999,
      "quote_volume": 1.42446737,
      "trades": 460
    },
    {
      "time": "2026-06-05T03:00:00+00:00",
      "open_time_ms": 1780628400000,
      "open": 0.02764,
      "high": 0.02767,
      "low": 0.02757,
      "close": 0.02765,
      "volume": 83.5112,
      "close_time_ms": 1780629299999,
      "quote_volume": 2.30691177,
      "trades": 631
    },
    {
      "time": "2026-06-05T03:15:00+00:00",
      "open_time_ms": 1780629300000,
      "open": 0.02765,
      "high": 0.02771,
      "low": 0.02762,
      "close": 0.02763,
      "volume": 68.4234,
      "close_time_ms": 1780630199999,
      "quote_volume": 1.89382535,
      "trades": 755
    },
    {
      "time": "2026-06-05T03:30:00+00:00",
      "open_time_ms": 1780630200000,
      "open": 0.02764,
      "high": 0.02766,
      "low": 0.02762,
      "close": 0.02763,
      "volume": 5.1953,
      "close_time_ms": 1780631099999,
      "quote_volume": 0.14360273,
      "trades": 220
    },
    {
      "time": "2026-06-05T03:45:00+00:00",
      "open_time_ms": 1780631100000,
      "open": 0.02763,
      "high": 0.02764,
      "low": 0.02756,
      "close": 0.02757,
      "volume": 33.7004,
      "close_time_ms": 1780631999999,
      "quote_volume": 0.92963775,
      "trades": 457
    },
    {
      "time": "2026-06-05T04:00:00+00:00",
      "open_time_ms": 1780632000000,
      "open": 0.02756,
      "high": 0.02757,
      "low": 0.02748,
      "close": 0.02748,
      "volume": 345.7487,
      "close_time_ms": 1780632899999,
      "quote_volume": 9.51773542,
      "trades": 1619
    },
    {
      "time": "2026-06-05T04:15:00+00:00",
      "open_time_ms": 1780632900000,
      "open": 0.02747,
      "high": 0.02747,
      "low": 0.02743,
      "close": 0.02746,
      "volume": 211.5311,
      "close_time_ms": 1780633799999,
      "quote_volume": 5.80566057,
      "trades": 1072
    },
    {
      "time": "2026-06-05T04:30:00+00:00",
      "open_time_ms": 1780633800000,
      "open": 0.02746,
      "high": 0.02747,
      "low": 0.02742,
      "close": 0.02746,
      "volume": 42.9827,
      "close_time_ms": 1780634699999,
      "quote_volume": 1.17959421,
      "trades": 415
    },
    {
      "time": "2026-06-05T04:45:00+00:00",
      "open_time_ms": 1780634700000,
      "open": 0.02746,
      "high": 0.02746,
      "low": 0.02741,
      "close": 0.02743,
      "volume": 181.9641,
      "close_time_ms": 1780635599999,
      "quote_volume": 4.99061226,
      "trades": 687
    },
    {
      "time": "2026-06-05T05:00:00+00:00",
      "open_time_ms": 1780635600000,
      "open": 0.02743,
      "high": 0.02745,
      "low": 0.02732,
      "close": 0.02735,
      "volume": 141.1214,
      "close_time_ms": 1780636499999,
      "quote_volume": 3.86316322,
      "trades": 1207
    },
    {
      "time": "2026-06-05T05:15:00+00:00",
      "open_time_ms": 1780636500000,
      "open": 0.02734,
      "high": 0.02735,
      "low": 0.02728,
      "close": 0.02733,
      "volume": 221.4334,
      "close_time_ms": 1780637399999,
      "quote_volume": 6.04741126,
      "trades": 1077
    },
    {
      "time": "2026-06-05T05:30:00+00:00",
      "open_time_ms": 1780637400000,
      "open": 0.02732,
      "high": 0.02732,
      "low": 0.02699,
      "close": 0.02703,
      "volume": 952.2959,
      "close_time_ms": 1780638299999,
      "quote_volume": 25.81997834,
      "trades": 4432
    },
    {
      "time": "2026-06-05T05:45:00+00:00",
      "open_time_ms": 1780638300000,
      "open": 0.02702,
      "high": 0.02709,
      "low": 0.0269,
      "close": 0.02703,
      "volume": 1196.1832,
      "close_time_ms": 1780639199999,
      "quote_volume": 32.24767499,
      "trades": 3610
    },
    {
      "time": "2026-06-05T06:00:00+00:00",
      "open_time_ms": 1780639200000,
      "open": 0.02702,
      "high": 0.02702,
      "low": 0.02685,
      "close": 0.02692,
      "volume": 1296.9602,
      "close_time_ms": 1780640099999,
      "quote_volume": 34.91931195,
      "trades": 3848
    },
    {
      "time": "2026-06-05T06:15:00+00:00",
      "open_time_ms": 1780640100000,
      "open": 0.02693,
      "high": 0.02695,
      "low": 0.02659,
      "close": 0.02666,
      "volume": 2062.1192,
      "close_time_ms": 1780640999999,
      "quote_volume": 55.18892827,
      "trades": 7164
    },
    {
      "time": "2026-06-05T06:30:00+00:00",
      "open_time_ms": 1780641000000,
      "open": 0.02667,
      "high": 0.02685,
      "low": 0.02665,
      "close": 0.02679,
      "volume": 550.3563,
      "close_time_ms": 1780641899999,
      "quote_volume": 14.71421005,
      "trades": 2095
    },
    {
      "time": "2026-06-05T06:45:00+00:00",
      "open_time_ms": 1780641900000,
      "open": 0.0268,
      "high": 0.0268,
      "low": 0.02673,
      "close": 0.02675,
      "volume": 392.4017,
      "close_time_ms": 1780642799999,
      "quote_volume": 10.50220126,
      "trades": 983
    },
    {
      "time": "2026-06-05T07:00:00+00:00",
      "open_time_ms": 1780642800000,
      "open": 0.02674,
      "high": 0.02675,
      "low": 0.02662,
      "close": 0.02663,
      "volume": 497.2121,
      "close_time_ms": 1780643699999,
      "quote_volume": 13.26234671,
      "trades": 1527
    },
    {
      "time": "2026-06-05T07:15:00+00:00",
      "open_time_ms": 1780643700000,
      "open": 0.02664,
      "high": 0.02671,
      "low": 0.02663,
      "close": 0.02663,
      "volume": 293.4719,
      "close_time_ms": 1780644599999,
      "quote_volume": 7.82867944,
      "trades": 1060
    },
    {
      "time": "2026-06-05T07:30:00+00:00",
      "open_time_ms": 1780644600000,
      "open": 0.02663,
      "high": 0.02665,
      "low": 0.02653,
      "close": 0.02663,
      "volume": 705.21,
      "close_time_ms": 1780645499999,
      "quote_volume": 18.75054578,
      "trades": 2317
    },
    {
      "time": "2026-06-05T07:45:00+00:00",
      "open_time_ms": 1780645500000,
      "open": 0.02662,
      "high": 0.02668,
      "low": 0.0266,
      "close": 0.02662,
      "volume": 240.8781,
      "close_time_ms": 1780646399999,
      "quote_volume": 6.41414334,
      "trades": 1183
    },
    {
      "time": "2026-06-05T08:00:00+00:00",
      "open_time_ms": 1780646400000,
      "open": 0.02661,
      "high": 0.02662,
      "low": 0.02657,
      "close": 0.02659,
      "volume": 285.8077,
      "close_time_ms": 1780647299999,
      "quote_volume": 7.60237626,
      "trades": 846
    },
    {
      "time": "2026-06-05T08:15:00+00:00",
      "open_time_ms": 1780647300000,
      "open": 0.02659,
      "high": 0.02664,
      "low": 0.02655,
      "close": 0.02664,
      "volume": 128.5697,
      "close_time_ms": 1780648199999,
      "quote_volume": 3.41885357,
      "trades": 637
    },
    {
      "time": "2026-06-05T08:30:00+00:00",
      "open_time_ms": 1780648200000,
      "open": 0.02663,
      "high": 0.0267,
      "low": 0.02663,
      "close": 0.02665,
      "volume": 125.0031,
      "close_time_ms": 1780649099999,
      "quote_volume": 3.33103088,
      "trades": 585
    },
    {
      "time": "2026-06-05T08:45:00+00:00",
      "open_time_ms": 1780649100000,
      "open": 0.02666,
      "high": 0.02668,
      "low": 0.02662,
      "close": 0.02664,
      "volume": 80.2051,
      "close_time_ms": 1780649999999,
      "quote_volume": 2.13750625,
      "trades": 472
    },
    {
      "time": "2026-06-05T09:00:00+00:00",
      "open_time_ms": 1780650000000,
      "open": 0.02664,
      "high": 0.02675,
      "low": 0.02663,
      "close": 0.02674,
      "volume": 271.2346,
      "close_time_ms": 1780650899999,
      "quote_volume": 7.24140341,
      "trades": 884
    },
    {
      "time": "2026-06-05T09:15:00+00:00",
      "open_time_ms": 1780650900000,
      "open": 0.02673,
      "high": 0.02674,
      "low": 0.02665,
      "close": 0.02669,
      "volume": 344.9462,
      "close_time_ms": 1780651799999,
      "quote_volume": 9.20989669,
      "trades": 892
    },
    {
      "time": "2026-06-05T09:30:00+00:00",
      "open_time_ms": 1780651800000,
      "open": 0.02669,
      "high": 0.02675,
      "low": 0.02669,
      "close": 0.02673,
      "volume": 149.1035,
      "close_time_ms": 1780652699999,
      "quote_volume": 3.98362172,
      "trades": 384
    },
    {
      "time": "2026-06-05T09:45:00+00:00",
      "open_time_ms": 1780652700000,
      "open": 0.02672,
      "high": 0.02677,
      "low": 0.02672,
      "close": 0.02677,
      "volume": 136.8984,
      "close_time_ms": 1780653599999,
      "quote_volume": 3.66098152,
      "trades": 560
    },
    {
      "time": "2026-06-05T10:00:00+00:00",
      "open_time_ms": 1780653600000,
      "open": 0.02677,
      "high": 0.02677,
      "low": 0.0267,
      "close": 0.02672,
      "volume": 248.4222,
      "close_time_ms": 1780654499999,
      "quote_volume": 6.64435006,
      "trades": 795
    },
    {
      "time": "2026-06-05T10:15:00+00:00",
      "open_time_ms": 1780654500000,
      "open": 0.02673,
      "high": 0.02679,
      "low": 0.02672,
      "close": 0.02679,
      "volume": 191.4402,
      "close_time_ms": 1780655399999,
      "quote_volume": 5.12202837,
      "trades": 1237
    },
    {
      "time": "2026-06-05T10:30:00+00:00",
      "open_time_ms": 1780655400000,
      "open": 0.02679,
      "high": 0.02685,
      "low": 0.02679,
      "close": 0.02681,
      "volume": 159.5548,
      "close_time_ms": 1780656299999,
      "quote_volume": 4.278851,
      "trades": 834
    },
    {
      "time": "2026-06-05T10:45:00+00:00",
      "open_time_ms": 1780656300000,
      "open": 0.0268,
      "high": 0.02681,
      "low": 0.02677,
      "close": 0.02681,
      "volume": 66.7702,
      "close_time_ms": 1780657199999,
      "quote_volume": 1.78916692,
      "trades": 284
    },
    {
      "time": "2026-06-05T11:00:00+00:00",
      "open_time_ms": 1780657200000,
      "open": 0.02682,
      "high": 0.02683,
      "low": 0.02678,
      "close": 0.0268,
      "volume": 118.441,
      "close_time_ms": 1780658099999,
      "quote_volume": 3.17456973,
      "trades": 434
    },
    {
      "time": "2026-06-05T11:15:00+00:00",
      "open_time_ms": 1780658100000,
      "open": 0.0268,
      "high": 0.02686,
      "low": 0.0268,
      "close": 0.02686,
      "volume": 149.3867,
      "close_time_ms": 1780658999999,
      "quote_volume": 4.01002742,
      "trades": 453
    },
    {
      "time": "2026-06-05T11:30:00+00:00",
      "open_time_ms": 1780659000000,
      "open": 0.02686,
      "high": 0.02687,
      "low": 0.02683,
      "close": 0.02684,
      "volume": 58.8548,
      "close_time_ms": 1780659899999,
      "quote_volume": 1.58043136,
      "trades": 293
    },
    {
      "time": "2026-06-05T11:45:00+00:00",
      "open_time_ms": 1780659900000,
      "open": 0.02685,
      "high": 0.02687,
      "low": 0.02683,
      "close": 0.02684,
      "volume": 74.5644,
      "close_time_ms": 1780660799999,
      "quote_volume": 2.00164709,
      "trades": 567
    },
    {
      "time": "2026-06-05T12:00:00+00:00",
      "open_time_ms": 1780660800000,
      "open": 0.02684,
      "high": 0.02688,
      "low": 0.02672,
      "close": 0.02673,
      "volume": 247.0133,
      "close_time_ms": 1780661699999,
      "quote_volume": 6.62213062,
      "trades": 930
    },
    {
      "time": "2026-06-05T12:15:00+00:00",
      "open_time_ms": 1780661700000,
      "open": 0.02673,
      "high": 0.02676,
      "low": 0.0267,
      "close": 0.02674,
      "volume": 61.1509,
      "close_time_ms": 1780662599999,
      "quote_volume": 1.63453845,
      "trades": 454
    },
    {
      "time": "2026-06-05T12:30:00+00:00",
      "open_time_ms": 1780662600000,
      "open": 0.02675,
      "high": 0.0268,
      "low": 0.02669,
      "close": 0.02674,
      "volume": 377.0485,
      "close_time_ms": 1780663499999,
      "quote_volume": 10.08513613,
      "trades": 1331
    },
    {
      "time": "2026-06-05T12:45:00+00:00",
      "open_time_ms": 1780663500000,
      "open": 0.02673,
      "high": 0.02675,
      "low": 0.02669,
      "close": 0.02674,
      "volume": 32.8672,
      "close_time_ms": 1780664399999,
      "quote_volume": 0.8780104,
      "trades": 326
    },
    {
      "time": "2026-06-05T13:00:00+00:00",
      "open_time_ms": 1780664400000,
      "open": 0.02675,
      "high": 0.02691,
      "low": 0.02675,
      "close": 0.02689,
      "volume": 174.5449,
      "close_time_ms": 1780665299999,
      "quote_volume": 4.68176546,
      "trades": 834
    },
    {
      "time": "2026-06-05T13:15:00+00:00",
      "open_time_ms": 1780665300000,
      "open": 0.02689,
      "high": 0.0269,
      "low": 0.02681,
      "close": 0.02681,
      "volume": 122.8282,
      "close_time_ms": 1780666199999,
      "quote_volume": 3.29862094,
      "trades": 737
    },
    {
      "time": "2026-06-05T13:30:00+00:00",
      "open_time_ms": 1780666200000,
      "open": 0.02681,
      "high": 0.02693,
      "low": 0.02675,
      "close": 0.02676,
      "volume": 318.6868,
      "close_time_ms": 1780667099999,
      "quote_volume": 8.56569701,
      "trades": 1222
    },
    {
      "time": "2026-06-05T13:45:00+00:00",
      "open_time_ms": 1780667100000,
      "open": 0.02677,
      "high": 0.0268,
      "low": 0.02652,
      "close": 0.0266,
      "volume": 806.7118,
      "close_time_ms": 1780667999999,
      "quote_volume": 21.5169224,
      "trades": 3471
    },
    {
      "time": "2026-06-05T14:00:00+00:00",
      "open_time_ms": 1780668000000,
      "open": 0.0266,
      "high": 0.02666,
      "low": 0.02634,
      "close": 0.02653,
      "volume": 6332.1392,
      "close_time_ms": 1780668899999,
      "quote_volume": 167.66298696,
      "trades": 10908
    },
    {
      "time": "2026-06-05T14:15:00+00:00",
      "open_time_ms": 1780668900000,
      "open": 0.02654,
      "high": 0.02659,
      "low": 0.02644,
      "close": 0.02654,
      "volume": 424.1582,
      "close_time_ms": 1780669799999,
      "quote_volume": 11.25422413,
      "trades": 2115
    },
    {
      "time": "2026-06-05T14:30:00+00:00",
      "open_time_ms": 1780669800000,
      "open": 0.02655,
      "high": 0.02657,
      "low": 0.02643,
      "close": 0.02646,
      "volume": 468.5779,
      "close_time_ms": 1780670699999,
      "quote_volume": 12.41861876,
      "trades": 2387
    },
    {
      "time": "2026-06-05T14:45:00+00:00",
      "open_time_ms": 1780670700000,
      "open": 0.02646,
      "high": 0.02647,
      "low": 0.02629,
      "close": 0.0263,
      "volume": 457.3303,
      "close_time_ms": 1780671599999,
      "quote_volume": 12.05590868,
      "trades": 1784
    },
    {
      "time": "2026-06-05T15:00:00+00:00",
      "open_time_ms": 1780671600000,
      "open": 0.0263,
      "high": 0.02632,
      "low": 0.02609,
      "close": 0.02614,
      "volume": 1048.9248,
      "close_time_ms": 1780672499999,
      "quote_volume": 27.46643638,
      "trades": 3779
    },
    {
      "time": "2026-06-05T15:15:00+00:00",
      "open_time_ms": 1780672500000,
      "open": 0.02615,
      "high": 0.02627,
      "low": 0.02611,
      "close": 0.02624,
      "volume": 695.1379,
      "close_time_ms": 1780673399999,
      "quote_volume": 18.20269596,
      "trades": 2480
    },
    {
      "time": "2026-06-05T15:30:00+00:00",
      "open_time_ms": 1780673400000,
      "open": 0.02623,
      "high": 0.02627,
      "low": 0.02618,
      "close": 0.02625,
      "volume": 846.3534,
      "close_time_ms": 1780674299999,
      "quote_volume": 22.18424098,
      "trades": 2583
    },
    {
      "time": "2026-06-05T15:45:00+00:00",
      "open_time_ms": 1780674300000,
      "open": 0.02625,
      "high": 0.02625,
      "low": 0.02614,
      "close": 0.0262,
      "volume": 904.3861,
      "close_time_ms": 1780675199999,
      "quote_volume": 23.69498873,
      "trades": 1752
    },
    {
      "time": "2026-06-05T16:00:00+00:00",
      "open_time_ms": 1780675200000,
      "open": 0.02619,
      "high": 0.0262,
      "low": 0.02587,
      "close": 0.02606,
      "volume": 2991.3451,
      "close_time_ms": 1780676099999,
      "quote_volume": 77.76490099,
      "trades": 7437
    },
    {
      "time": "2026-06-05T16:15:00+00:00",
      "open_time_ms": 1780676100000,
      "open": 0.02606,
      "high": 0.02622,
      "low": 0.02601,
      "close": 0.02616,
      "volume": 1974.1745,
      "close_time_ms": 1780676999999,
      "quote_volume": 51.55722604,
      "trades": 5232
    },
    {
      "time": "2026-06-05T16:30:00+00:00",
      "open_time_ms": 1780677000000,
      "open": 0.02616,
      "high": 0.02618,
      "low": 0.026,
      "close": 0.02603,
      "volume": 269.9931,
      "close_time_ms": 1780677899999,
      "quote_volume": 7.03937801,
      "trades": 1297
    },
    {
      "time": "2026-06-05T16:45:00+00:00",
      "open_time_ms": 1780677900000,
      "open": 0.02603,
      "high": 0.02622,
      "low": 0.02602,
      "close": 0.02619,
      "volume": 258.8359,
      "close_time_ms": 1780678799999,
      "quote_volume": 6.76147191,
      "trades": 1400
    },
    {
      "time": "2026-06-05T17:00:00+00:00",
      "open_time_ms": 1780678800000,
      "open": 0.0262,
      "high": 0.02624,
      "low": 0.02617,
      "close": 0.0262,
      "volume": 315.7837,
      "close_time_ms": 1780679699999,
      "quote_volume": 8.27648525,
      "trades": 903
    },
    {
      "time": "2026-06-05T17:15:00+00:00",
      "open_time_ms": 1780679700000,
      "open": 0.02619,
      "high": 0.0262,
      "low": 0.02613,
      "close": 0.02618,
      "volume": 184.2436,
      "close_time_ms": 1780680599999,
      "quote_volume": 4.82068922,
      "trades": 753
    },
    {
      "time": "2026-06-05T17:30:00+00:00",
      "open_time_ms": 1780680600000,
      "open": 0.02618,
      "high": 0.02624,
      "low": 0.02616,
      "close": 0.02621,
      "volume": 189.1123,
      "close_time_ms": 1780681499999,
      "quote_volume": 4.9551455,
      "trades": 591
    },
    {
      "time": "2026-06-05T17:45:00+00:00",
      "open_time_ms": 1780681500000,
      "open": 0.02622,
      "high": 0.02623,
      "low": 0.02618,
      "close": 0.02621,
      "volume": 141.6444,
      "close_time_ms": 1780682399999,
      "quote_volume": 3.71108702,
      "trades": 636
    },
    {
      "time": "2026-06-05T18:00:00+00:00",
      "open_time_ms": 1780682400000,
      "open": 0.02622,
      "high": 0.02625,
      "low": 0.0262,
      "close": 0.02621,
      "volume": 105.8578,
      "close_time_ms": 1780683299999,
      "quote_volume": 2.77626122,
      "trades": 582
    },
    {
      "time": "2026-06-05T18:15:00+00:00",
      "open_time_ms": 1780683300000,
      "open": 0.02621,
      "high": 0.02624,
      "low": 0.02602,
      "close": 0.02602,
      "volume": 625.253,
      "close_time_ms": 1780684199999,
      "quote_volume": 16.33472025,
      "trades": 1531
    },
    {
      "time": "2026-06-05T18:30:00+00:00",
      "open_time_ms": 1780684200000,
      "open": 0.02602,
      "high": 0.02613,
      "low": 0.02599,
      "close": 0.0261,
      "volume": 460.6701,
      "close_time_ms": 1780685099999,
      "quote_volume": 12.00154853,
      "trades": 2269
    },
    {
      "time": "2026-06-05T18:45:00+00:00",
      "open_time_ms": 1780685100000,
      "open": 0.02611,
      "high": 0.02619,
      "low": 0.02604,
      "close": 0.02615,
      "volume": 840.4558,
      "close_time_ms": 1780685999999,
      "quote_volume": 21.94846509,
      "trades": 3247
    },
    {
      "time": "2026-06-05T19:00:00+00:00",
      "open_time_ms": 1780686000000,
      "open": 0.02615,
      "high": 0.02621,
      "low": 0.02608,
      "close": 0.02612,
      "volume": 383.0756,
      "close_time_ms": 1780686899999,
      "quote_volume": 10.00646249,
      "trades": 2045
    },
    {
      "time": "2026-06-05T19:15:00+00:00",
      "open_time_ms": 1780686900000,
      "open": 0.02613,
      "high": 0.02613,
      "low": 0.02603,
      "close": 0.02607,
      "volume": 284.1277,
      "close_time_ms": 1780687799999,
      "quote_volume": 7.40912686,
      "trades": 1492
    },
    {
      "time": "2026-06-05T19:30:00+00:00",
      "open_time_ms": 1780687800000,
      "open": 0.02608,
      "high": 0.02608,
      "low": 0.02597,
      "close": 0.026,
      "volume": 286.5927,
      "close_time_ms": 1780688699999,
      "quote_volume": 7.45248253,
      "trades": 1300
    },
    {
      "time": "2026-06-05T19:45:00+00:00",
      "open_time_ms": 1780688700000,
      "open": 0.026,
      "high": 0.02615,
      "low": 0.026,
      "close": 0.0261,
      "volume": 477.6906,
      "close_time_ms": 1780689599999,
      "quote_volume": 12.45891863,
      "trades": 1962
    },
    {
      "time": "2026-06-05T20:00:00+00:00",
      "open_time_ms": 1780689600000,
      "open": 0.02611,
      "high": 0.02611,
      "low": 0.02596,
      "close": 0.02602,
      "volume": 637.5497,
      "close_time_ms": 1780690499999,
      "quote_volume": 16.59808397,
      "trades": 2101
    },
    {
      "time": "2026-06-05T20:15:00+00:00",
      "open_time_ms": 1780690500000,
      "open": 0.02603,
      "high": 0.02625,
      "low": 0.02603,
      "close": 0.02618,
      "volume": 469.6139,
      "close_time_ms": 1780691399999,
      "quote_volume": 12.28858325,
      "trades": 1905
    },
    {
      "time": "2026-06-05T20:30:00+00:00",
      "open_time_ms": 1780691400000,
      "open": 0.02617,
      "high": 0.02619,
      "low": 0.02609,
      "close": 0.0261,
      "volume": 223.1607,
      "close_time_ms": 1780692299999,
      "quote_volume": 5.83248397,
      "trades": 1034
    },
    {
      "time": "2026-06-05T20:45:00+00:00",
      "open_time_ms": 1780692300000,
      "open": 0.02609,
      "high": 0.02612,
      "low": 0.026,
      "close": 0.02602,
      "volume": 142.5204,
      "close_time_ms": 1780693199999,
      "quote_volume": 3.71091849,
      "trades": 863
    },
    {
      "time": "2026-06-05T21:00:00+00:00",
      "open_time_ms": 1780693200000,
      "open": 0.02602,
      "high": 0.02609,
      "low": 0.02602,
      "close": 0.02608,
      "volume": 116.9677,
      "close_time_ms": 1780694099999,
      "quote_volume": 3.0484953,
      "trades": 785
    },
    {
      "time": "2026-06-05T21:15:00+00:00",
      "open_time_ms": 1780694100000,
      "open": 0.02608,
      "high": 0.02618,
      "low": 0.02606,
      "close": 0.02617,
      "volume": 1357.1264,
      "close_time_ms": 1780694999999,
      "quote_volume": 35.48459537,
      "trades": 3208
    },
    {
      "time": "2026-06-05T21:30:00+00:00",
      "open_time_ms": 1780695000000,
      "open": 0.02617,
      "high": 0.02618,
      "low": 0.02608,
      "close": 0.02609,
      "volume": 150.1996,
      "close_time_ms": 1780695899999,
      "quote_volume": 3.92612436,
      "trades": 968
    },
    {
      "time": "2026-06-05T21:45:00+00:00",
      "open_time_ms": 1780695900000,
      "open": 0.02608,
      "high": 0.02618,
      "low": 0.02608,
      "close": 0.0261,
      "volume": 39.2298,
      "close_time_ms": 1780696799999,
      "quote_volume": 1.0245981,
      "trades": 944
    },
    {
      "time": "2026-06-05T22:00:00+00:00",
      "open_time_ms": 1780696800000,
      "open": 0.02611,
      "high": 0.02612,
      "low": 0.02593,
      "close": 0.02597,
      "volume": 479.2313,
      "close_time_ms": 1780697699999,
      "quote_volume": 12.46749652,
      "trades": 1407
    },
    {
      "time": "2026-06-05T22:15:00+00:00",
      "open_time_ms": 1780697700000,
      "open": 0.02597,
      "high": 0.02602,
      "low": 0.0259,
      "close": 0.02593,
      "volume": 753.3026,
      "close_time_ms": 1780698599999,
      "quote_volume": 19.55453056,
      "trades": 2201
    },
    {
      "time": "2026-06-05T22:30:00+00:00",
      "open_time_ms": 1780698600000,
      "open": 0.02594,
      "high": 0.02595,
      "low": 0.02589,
      "close": 0.0259,
      "volume": 220.7705,
      "close_time_ms": 1780699499999,
      "quote_volume": 5.72314251,
      "trades": 882
    },
    {
      "time": "2026-06-05T22:45:00+00:00",
      "open_time_ms": 1780699500000,
      "open": 0.02589,
      "high": 0.02594,
      "low": 0.02581,
      "close": 0.02594,
      "volume": 354.4913,
      "close_time_ms": 1780700399999,
      "quote_volume": 9.16790831,
      "trades": 1212
    },
    {
      "time": "2026-06-05T23:00:00+00:00",
      "open_time_ms": 1780700400000,
      "open": 0.02593,
      "high": 0.02599,
      "low": 0.02588,
      "close": 0.02592,
      "volume": 203.3521,
      "close_time_ms": 1780701299999,
      "quote_volume": 5.27664737,
      "trades": 773
    }
  ]
}
